package com.google.android.gms.fitness.request;

import android.os.Binder;
import android.os.IBinder;
import android.os.IInterface;
import android.os.Parcel;
import android.os.Parcelable.Creator;
import android.os.RemoteException;
import com.google.android.gms.fitness.data.BleDevice;

public abstract interface l
  extends IInterface
{
  public abstract void onDeviceFound(BleDevice paramBleDevice)
    throws RemoteException;
  
  public abstract void onScanStopped()
    throws RemoteException;
  
  public static abstract class a
    extends Binder
    implements l
  {
    public a()
    {
      attachInterface(this, "com.google.android.gms.fitness.request.IBleScanCallback");
    }
    
    public static l ay(IBinder paramIBinder)
    {
      if (paramIBinder == null) {
        return null;
      }
      IInterface localIInterface = paramIBinder.queryLocalInterface("com.google.android.gms.fitness.request.IBleScanCallback");
      if ((localIInterface != null) && ((localIInterface instanceof l))) {
        return (l)localIInterface;
      }
      return new a(paramIBinder);
    }
    
    public IBinder asBinder()
    {
      return this;
    }
    
    public boolean onTransact(int paramInt1, Parcel paramParcel1, Parcel paramParcel2, int paramInt2)
      throws RemoteException
    {
      switch (paramInt1)
      {
      default: 
        return super.onTransact(paramInt1, paramParcel1, paramParcel2, paramInt2);
      case 1598968902: 
        paramParcel2.writeString("com.google.android.gms.fitness.request.IBleScanCallback");
        return true;
      case 1: 
        paramParcel1.enforceInterface("com.google.android.gms.fitness.request.IBleScanCallback");
        if (paramParcel1.readInt() != 0) {}
        for (paramParcel1 = (BleDevice)BleDevice.CREATOR.createFromParcel(paramParcel1);; paramParcel1 = null)
        {
          onDeviceFound(paramParcel1);
          return true;
        }
      }
      paramParcel1.enforceInterface("com.google.android.gms.fitness.request.IBleScanCallback");
      onScanStopped();
      return true;
    }
    
    private static class a
      implements l
    {
      private IBinder lb;
      
      a(IBinder paramIBinder)
      {
        this.lb = paramIBinder;
      }
      
      public IBinder asBinder()
      {
        return this.lb;
      }
      
      /* Error */
      public void onDeviceFound(BleDevice paramBleDevice)
        throws RemoteException
      {
        // Byte code:
        //   0: invokestatic 31	android/os/Parcel:obtain	()Landroid/os/Parcel;
        //   3: astore_2
        //   4: aload_2
        //   5: ldc 33
        //   7: invokevirtual 37	android/os/Parcel:writeInterfaceToken	(Ljava/lang/String;)V
        //   10: aload_1
        //   11: ifnull +33 -> 44
        //   14: aload_2
        //   15: iconst_1
        //   16: invokevirtual 41	android/os/Parcel:writeInt	(I)V
        //   19: aload_1
        //   20: aload_2
        //   21: iconst_0
        //   22: invokevirtual 47	com/google/android/gms/fitness/data/BleDevice:writeToParcel	(Landroid/os/Parcel;I)V
        //   25: aload_0
        //   26: getfield 18	com/google/android/gms/fitness/request/l$a$a:lb	Landroid/os/IBinder;
        //   29: iconst_1
        //   30: aload_2
        //   31: aconst_null
        //   32: iconst_1
        //   33: invokeinterface 53 5 0
        //   38: pop
        //   39: aload_2
        //   40: invokevirtual 56	android/os/Parcel:recycle	()V
        //   43: return
        //   44: aload_2
        //   45: iconst_0
        //   46: invokevirtual 41	android/os/Parcel:writeInt	(I)V
        //   49: goto -24 -> 25
        //   52: astore_1
        //   53: aload_2
        //   54: invokevirtual 56	android/os/Parcel:recycle	()V
        //   57: aload_1
        //   58: athrow
        // Local variable table:
        //   start	length	slot	name	signature
        //   0	59	0	this	a
        //   0	59	1	paramBleDevice	BleDevice
        //   3	51	2	localParcel	Parcel
        // Exception table:
        //   from	to	target	type
        //   4	10	52	finally
        //   14	25	52	finally
        //   25	39	52	finally
        //   44	49	52	finally
      }
      
      public void onScanStopped()
        throws RemoteException
      {
        Parcel localParcel = Parcel.obtain();
        try
        {
          localParcel.writeInterfaceToken("com.google.android.gms.fitness.request.IBleScanCallback");
          this.lb.transact(2, localParcel, null, 1);
          return;
        }
        finally
        {
          localParcel.recycle();
        }
      }
    }
  }
}


/* Location:              /Users/michael/Downloads/dex2jar-2.0/GO_JEK.jar!/com/google/android/gms/fitness/request/l.class
 * Java compiler version: 6 (50.0)
 * JD-Core Version:       0.7.1
 */